rtl/Dockerfile
rtl/__init__.py
rtl/rtl.py
rtl/examples/__init__.py
rtl/examples/shell/__init__.py
rtl/examples/shell/ctf_2023.rtl
rtl/examples/shell/executable_binary.rtl
rtl/examples/shell/executable_binary_inline.rtl
rtl/examples/shell/executable_script.rtl
rtl/examples/shell/executable_script_inline.rtl
rtl/examples/shell/executable_script_inline_obfuscated.rtl
rtl/examples/shell/executable_script_obfuscated.rtl
rtl/examples/shell/executable_script_path.rtl
rtl/examples/shell/executable_script_ssh.rtl
rtl/examples/shell/failure_unknown_script.rtl
rtl/examples/shell/openssl_reverse_shell.rtl
rtl/examples/shell/shell_double_executable.rtl
rtl/examples/shell/shell_executable.rtl
rtl/examples/ssh/executable_script_ssh.rtl
rtl/lib/__init__.py
rtl/lib/protocol/__init__.py
rtl/lib/protocol/common/Makefile
rtl/lib/protocol/common/__init__.py
rtl/lib/protocol/common/main.c
rtl/lib/protocol/common/rtl_common.c
rtl/lib/protocol/common/rtl_common.h
rtl/lib/protocol/shell/Makefile
rtl/lib/protocol/shell/__init__.py
rtl/lib/protocol/shell/main.c
rtl/lib/protocol/shell/shell.c
rtl/lib/protocol/shell/shell.h
rtl/lib/protocol/ssh/Makefile
rtl/lib/protocol/ssh/__init__.py
rtl/lib/protocol/ssh/main.c
rtl/lib/protocol/ssh/ssh.c
rtl/lib/protocol/ssh/ssh.h
rtl/lib/protocol/ssh/libssh2/build/Makefile
rtl/lib/protocol/ssh/libssh2/build/CMakeFiles/3.22.1/CompilerIdC/CMakeCCompilerId.c
rtl/lib/protocol/ssh/libssh2/build/CMakeFiles/CheckIncludeFiles/HAVE_ARPA_INET_H.c
rtl/lib/protocol/ssh/libssh2/build/CMakeFiles/CheckIncludeFiles/HAVE_INTTYPES_H.c
rtl/lib/protocol/ssh/libssh2/build/CMakeFiles/CheckIncludeFiles/HAVE_NETINET_IN_H.c
rtl/lib/protocol/ssh/libssh2/build/CMakeFiles/CheckIncludeFiles/HAVE_SYS_IOCTL_H.c
rtl/lib/protocol/ssh/libssh2/build/CMakeFiles/CheckIncludeFiles/HAVE_SYS_PARAM_H.c
rtl/lib/protocol/ssh/libssh2/build/CMakeFiles/CheckIncludeFiles/HAVE_SYS_SELECT_H.c
rtl/lib/protocol/ssh/libssh2/build/CMakeFiles/CheckIncludeFiles/HAVE_SYS_SOCKET_H.c
red_team_language-0.2.0.dist-info/LICENSE
red_team_language-0.2.0.dist-info/METADATA
red_team_language-0.2.0.dist-info/WHEEL
red_team_language-0.2.0.dist-info/entry_points.txt
red_team_language-0.2.0.dist-info/top_level.txt
red_team_language-0.2.0.dist-info/zip-safe
red_team_language-0.2.0.dist-info/RECORD
