Metadata-Version: 2.1
Name: red-team-language
Version: 0.2.0
Summary: Red-Team-Language - something snazzy
Home-page: https://github.com/ArchiMoebius/rtl
Download-URL: https://github.com/ArchiMoebius/rtl
Author: Archi Moebius
Author-email: ArchiMoebius@dojobebo.com
Maintainer: Archi Moebius
Maintainer-email: ArchiMoebius@dojobebo.com
License: GPL-3 LGPL-3
Project-URL: Docs, https://github.com/ArchiMoebius/rtl/README.md
Project-URL: Bugs, https://github.com/ArchiMoebius/rtl/issues
Project-URL: C.I., https://github.com/ArchiMoebius/rtl/
Keywords: python3
Platform: Linux
Classifier: Development Status :: 1 - Planning
Classifier: Environment :: Console
Classifier: Environment :: Other Environment
Classifier: Intended Audience :: Developers
Classifier: Intended Audience :: Other Audience
Classifier: Natural Language :: English
Classifier: License :: OSI Approved :: GNU General Public License (GPL)
Classifier: License :: OSI Approved :: GNU Library or Lesser General Public License (LGPL)
Classifier: License :: OSI Approved :: GNU Lesser General Public License v3 or later (LGPLv3+)
Classifier: License :: OSI Approved :: GNU General Public License v3 or later (GPLv3+)
Classifier: Operating System :: POSIX :: Linux
Classifier: Programming Language :: Python
Classifier: Programming Language :: Python :: 3
Classifier: Programming Language :: Python :: 3 :: Only
Classifier: Programming Language :: Python :: 3.10
Classifier: Topic :: Software Development
Provides: red_team_language
Requires-Python: >=3.10
License-File: LICENSE
Requires-Dist: pip
Requires-Dist: llvmlite
